icpy/ICP.py
icpy/__init__.py
ICPy-0.0.6.dist-info/LICENSE
ICPy-0.0.6.dist-info/METADATA
ICPy-0.0.6.dist-info/WHEEL
ICPy-0.0.6.dist-info/top_level.txt
ICPy-0.0.6.dist-info/RECORD
