Metadata-Version: 2.1
Name: ICPy
Version: 0.0.6
Summary: Invariant Causal Prediction for python
Author-email: Jan Gleixner <jan.gleixner+icpy@gmail.com>
Maintainer-email: Jan Gleixner <jan.gleixner+icpy@gmail.com>
Project-URL: source, https://github.com/jan-glx/ICPy
Keywords: statistics,casual-inference
Classifier: License :: OSI Approved :: MIT License
Classifier: Programming Language :: Python :: 2
Classifier: Programming Language :: Python :: 2.7
Classifier: Programming Language :: Python :: 3
Classifier: Programming Language :: Python :: 3.4
Classifier: Programming Language :: Python :: 3.5
Classifier: Programming Language :: Python :: 3.6
Requires-Python: !=3.0.*,!=3.1.*,!=3.2.*,!=3.3.*,>=2.7
License-File: LICENSE
Requires-Dist: numpy
Requires-Dist: scipy
Requires-Dist: scikit-learn
Provides-Extra: doc
Requires-Dist: sphinx ; extra == 'doc'
Requires-Dist: furo ; extra == 'doc'
Requires-Dist: myst-parser ; extra == 'doc'
Provides-Extra: test
Requires-Dist: pytest ; extra == 'test'
Requires-Dist: coverage[toml] ; extra == 'test'
Requires-Dist: scipy >=1.7.0 ; extra == 'test'
